{
  "name": "webpack_code",
  "version": "1.0.0",
  "description": "",
  "main": "index.js",
  "scripts": {
    "test": "echo \"Error: no test specified\" && exit 1"
  },
  "author": "",
  "license": "ISC",
  "dependencies": {
    "asset": "^0.4.13",
    "file-loader": "^6.2.0",
    "html-loader": "^3.1.0",
    "html-webpack-plugin": "^5.5.0",
    "less": "^4.1.2",
    "less-loader": "^10.2.0",
    "mini-css-extract-plugin": "^2.6.0",
    "postcss-loader": "^6.2.1",
    "postcss-preset-env": "^7.4.3",
    "url-loader": "^4.1.1",
    "webpack-dev-server": "^4.7.4"
  },
  "devDependencies": {
    "css-loader": "^6.7.1",
    "style-loader": "^3.3.1",
    "webpack": "^5.70.0",
    "webpack-cli": "^4.9.2"
  },
  "browserlist":{
    "development":[
      "last 1 chrome version",
      "last 1 firefox version",
      "last 1 safari version"
    ],
    "production":[
      ">0.2%",
      "no dead",
      ""
    ]
  }
}
